dada2_pplacer/__init__.py
dada2_pplacer/dada2_seqtab_to_pplacer.py
dada2_pplacer/dada2_taxonomy_to_tallies_wide.py
dada2_pplacer-0.9.0.dist-info/METADATA
dada2_pplacer-0.9.0.dist-info/WHEEL
dada2_pplacer-0.9.0.dist-info/entry_points.txt
dada2_pplacer-0.9.0.dist-info/top_level.txt
dada2_pplacer-0.9.0.dist-info/RECORD
