Metadata-Version: 2.1
Name: dada2-pplacer
Version: 0.9.0
Summary: Convert output from dada2 to be compatible with pplacer / guppy / rppr pipelines
Home-page: https://github.com/jgolob/dada2-pplacer/
Author: Jonathan Golob
Author-email: j-dev@golob.org
License: MIT
Requires-Dist: numpy >=1.13.3
Requires-Dist: pandas >=2.0.0
